curd/__init__.py
curd/errors.py
curd/session.py
curd/connections/__init__.py
curd/connections/cassandra.py
curd/connections/hbase.py
curd/connections/mysql.py
curd/connections/utils/__init__.py
curd/connections/utils/cql.py
curd/connections/utils/sql.py
tests/__init__.py
tests/conf.py
tests/operations.py
tests/test_cassandra.py
tests/test_hbase.py
tests/test_mysql.py
yicurd-1.0.0.dist-info/LICENSE
yicurd-1.0.0.dist-info/METADATA
yicurd-1.0.0.dist-info/WHEEL
yicurd-1.0.0.dist-info/top_level.txt
yicurd-1.0.0.dist-info/RECORD
